{"lang": "Mysterious Language", "title": "409B - Mysterious Language", "time": "0ms", "verdict": "COMPILATION_ERROR", "memory": "0KB", "problem_link": "/problemset/problem/409/B", "problem_id": "6239896"}
{"lang": "GNU C++", "title": "359A - Table", "time": "15ms", "verdict": "OK", "memory": "0KB", "problem_link": "/problemset/problem/359/A", "problem_id": "4964536"}
{"lang": "GNU C++", "title": "359A - Table", "time": "0ms", "verdict": "WRONG_ANSWER", "memory": "200KB", "problem_link": "/problemset/problem/359/A", "problem_id": "4964046"}
{"lang": "GNU C++", "title": "359A - Table", "time": "15ms", "verdict": "WRONG_ANSWER", "memory": "200KB", "problem_link": "/problemset/problem/359/A", "problem_id": "4963261"}
{"lang": "GNU C++", "title": "359A - Table", "time": "0ms", "verdict": "WRONG_ANSWER", "memory": "200KB", "problem_link": "/problemset/problem/359/A", "problem_id": "4963004"}
{"lang": "GNU C++", "title": "263A - Beautiful Matrix", "time": "30ms", "verdict": "OK", "memory": "0KB", "problem_link": "/problemset/problem/263/A", "problem_id": "4821550"}
{"lang": "GNU C++", "title": "355D - Game with Strings", "time": "15ms", "verdict": "WRONG_ANSWER", "memory": "0KB", "problem_link": "/problemset/problem/355/D", "problem_id": "4819989"}
{"lang": "GNU C++", "title": "355D - Game with Strings", "time": "0ms", "verdict": "WRONG_ANSWER", "memory": "0KB", "problem_link": "/problemset/problem/355/D", "problem_id": "4819984"}
{"lang": "Python 2", "title": "1B - Spreadsheet", "time": "1154ms", "verdict": "OK", "memory": "1600KB", "problem_link": "/problemset/problem/1/B", "problem_id": "4704119"}
{"lang": "Python 2", "title": "1B - Spreadsheet", "time": "30ms", "verdict": "WRONG_ANSWER", "memory": "0KB", "problem_link": "/problemset/problem/1/B", "problem_id": "4704061"}
{"lang": "GNU C++", "title": "1B - Spreadsheet", "time": "0ms", "verdict": "COMPILATION_ERROR", "memory": "0KB", "problem_link": "/problemset/problem/1/B", "problem_id": "4704052"}
{"lang": "GNU C++", "title": "352C - Jeff and Rounding", "time": "0ms", "verdict": "WRONG_ANSWER", "memory": "0KB", "problem_link": "/problemset/problem/352/C", "problem_id": "4700711"}
{"lang": "GNU C++", "title": "352C - Jeff and Rounding", "time": "0ms", "verdict": "WRONG_ANSWER", "memory": "0KB", "problem_link": "/problemset/problem/352/C", "problem_id": "4700690"}
{"lang": "GNU C++", "title": "352C - Jeff and Rounding", "time": "0ms", "verdict": "WRONG_ANSWER", "memory": "0KB", "problem_link": "/problemset/problem/352/C", "problem_id": "4700685"}
{"lang": "GNU C++", "title": "352C - Jeff and Rounding", "time": "0ms", "verdict": "WRONG_ANSWER", "memory": "0KB", "problem_link": "/problemset/problem/352/C", "problem_id": "4700676"}
{"lang": "GNU C++", "title": "352C - Jeff and Rounding", "time": "0ms", "verdict": "WRONG_ANSWER", "memory": "0KB", "problem_link": "/problemset/problem/352/C", "problem_id": "4700665"}
{"lang": "GNU C++", "title": "352C - Jeff and Rounding", "time": "0ms", "verdict": "WRONG_ANSWER", "memory": "0KB", "problem_link": "/problemset/problem/352/C", "problem_id": "4700619"}
{"lang": "GNU C++", "title": "352C - Jeff and Rounding", "time": "0ms", "verdict": "WRONG_ANSWER", "memory": "0KB", "problem_link": "/problemset/problem/352/C", "problem_id": "4700607"}
{"lang": "GNU C++", "title": "352C - Jeff and Rounding", "time": "0ms", "verdict": "WRONG_ANSWER", "memory": "0KB", "problem_link": "/problemset/problem/352/C", "problem_id": "4700601"}
{"lang": "GNU C++", "title": "352C - Jeff and Rounding", "time": "0ms", "verdict": "WRONG_ANSWER", "memory": "0KB", "problem_link": "/problemset/problem/352/C", "problem_id": "4700595"}
{"lang": "GNU C++0x", "title": "352C - Jeff and Rounding", "time": "0ms", "verdict": "WRONG_ANSWER", "memory": "0KB", "problem_link": "/problemset/problem/352/C", "problem_id": "4700578"}
{"lang": "GNU C++", "title": "352C - Jeff and Rounding", "time": "0ms", "verdict": "WRONG_ANSWER", "memory": "0KB", "problem_link": "/problemset/problem/352/C", "problem_id": "4700566"}
{"lang": "GNU C++", "title": "352C - Jeff and Rounding", "time": "0ms", "verdict": "WRONG_ANSWER", "memory": "0KB", "problem_link": "/problemset/problem/352/C", "problem_id": "4700554"}
{"lang": "Python 2", "title": "352B - Jeff and Periods", "time": "498ms", "verdict": "OK", "memory": "17900KB", "problem_link": "/problemset/problem/352/B", "problem_id": "4666943"}
{"lang": "Python 2", "title": "352B - Jeff and Periods", "time": "62ms", "verdict": "WRONG_ANSWER", "memory": "900KB", "problem_link": "/problemset/problem/352/B", "problem_id": "4666648"}
{"lang": "Python 2", "title": "352B - Jeff and Periods", "time": "92ms", "verdict": "WRONG_ANSWER", "memory": "900KB", "problem_link": "/problemset/problem/352/B", "problem_id": "4666597"}
{"lang": "Python 2", "title": "352B - Jeff and Periods", "time": "92ms", "verdict": "WRONG_ANSWER", "memory": "900KB", "problem_link": "/problemset/problem/352/B", "problem_id": "4666514"}
{"lang": "Python 2", "title": "352B - Jeff and Periods", "time": "92ms", "verdict": "WRONG_ANSWER", "memory": "900KB", "problem_link": "/problemset/problem/352/B", "problem_id": "4666395"}
{"lang": "Python 2", "title": "352B - Jeff and Periods", "time": "30ms", "verdict": "WRONG_ANSWER", "memory": "900KB", "problem_link": "/problemset/problem/352/B", "problem_id": "4666216"}
{"lang": "Python 2", "title": "352B - Jeff and Periods", "time": "62ms", "verdict": "WRONG_ANSWER", "memory": "900KB", "problem_link": "/problemset/problem/352/B", "problem_id": "4666104"}
{"lang": "Python 2", "title": "352B - Jeff and Periods", "time": "92ms", "verdict": "WRONG_ANSWER", "memory": "900KB", "problem_link": "/problemset/problem/352/B", "problem_id": "4665086"}
{"lang": "Python 2", "title": "352A - Jeff and Digits", "time": "62ms", "verdict": "OK", "memory": "0KB", "problem_link": "/problemset/problem/352/A", "problem_id": "4661440"}
{"lang": "Python 2", "title": "352A - Jeff and Digits", "time": "62ms", "verdict": "WRONG_ANSWER", "memory": "0KB", "problem_link": "/problemset/problem/352/A", "problem_id": "4660556"}
{"lang": "Python 2", "title": "50A - Domino piling", "time": "62ms", "verdict": "OK", "memory": "0KB", "problem_link": "/problemset/problem/50/A", "problem_id": "4618683"}
{"lang": "Python 2", "title": "158B - Taxi", "time": "248ms", "verdict": "OK", "memory": "2300KB", "problem_link": "/problemset/problem/158/B", "problem_id": "4618628"}
{"lang": "Python 2", "title": "118A - String Task", "time": "92ms", "verdict": "OK", "memory": "0KB", "problem_link": "/problemset/problem/118/A", "problem_id": "4618510"}
{"lang": "Python 2", "title": "71A - Way Too Long Words", "time": "92ms", "verdict": "OK", "memory": "0KB", "problem_link": "/problemset/problem/71/A", "problem_id": "4611933"}
{"lang": "Python 2", "title": "71A - Way Too Long Words", "time": "62ms", "verdict": "WRONG_ANSWER", "memory": "0KB", "problem_link": "/problemset/problem/71/A", "problem_id": "4611920"}
{"lang": "Python 2", "title": "4A - Watermelon", "time": "62ms", "verdict": "OK", "memory": "0KB", "problem_link": "/problemset/problem/4/A", "problem_id": "4610807"}
{"lang": "Python 2", "title": "4A - Watermelon", "time": "62ms", "verdict": "WRONG_ANSWER", "memory": "0KB", "problem_link": "/problemset/problem/4/A", "problem_id": "4610791"}
{"lang": "Python 2", "title": "1B - Spreadsheet", "time": "62ms", "verdict": "WRONG_ANSWER", "memory": "0KB", "problem_link": "/problemset/problem/1/B", "problem_id": "4601136"}
{"lang": "Python 2", "title": "1B - Spreadsheet", "time": "62ms", "verdict": "RUNTIME_ERROR", "memory": "0KB", "problem_link": "/problemset/problem/1/B", "problem_id": "4601131"}
{"lang": "Python 2", "title": "1A - Theatre Square", "time": "92ms", "verdict": "OK", "memory": "0KB", "problem_link": "/problemset/problem/1/A", "problem_id": "4600811"}
{"lang": "Python 2", "title": "1A - Theatre Square", "time": "30ms", "verdict": "WRONG_ANSWER", "memory": "0KB", "problem_link": "/problemset/problem/1/A", "problem_id": "4600798"}
{"lang": "Python 2", "title": "1A - Theatre Square", "time": "92ms", "verdict": "WRONG_ANSWER", "memory": "0KB", "problem_link": "/problemset/problem/1/A", "problem_id": "4600794"}
{"lang": "Python 2", "title": "349C - Mafia", "time": "186ms", "verdict": "OK", "memory": "5700KB", "problem_link": "/problemset/problem/349/C", "problem_id": "4596497"}
{"lang": "GNU C++", "title": "347A - Difference Row", "time": "30ms", "verdict": "OK", "memory": "0KB", "problem_link": "/problemset/problem/347/A", "problem_id": "4529014"}
{"lang": "GNU C++", "title": "347A - Difference Row", "time": "0ms", "verdict": "RUNTIME_ERROR", "memory": "0KB", "problem_link": "/problemset/problem/347/A", "problem_id": "4529009"}
{"lang": "GNU C++", "title": "347B - Fixed Points", "time": "124ms", "verdict": "OK", "memory": "1100KB", "problem_link": "/problemset/problem/347/B", "problem_id": "4528645"}
{"lang": "GNU C++", "title": "347B - Fixed Points", "time": "0ms", "verdict": "COMPILATION_ERROR", "memory": "0KB", "problem_link": "/problemset/problem/347/B", "problem_id": "4528637"}
{"lang": "GNU C++", "title": "347A - Difference Row", "time": "30ms", "verdict": "WRONG_ANSWER", "memory": "0KB", "problem_link": "/problemset/problem/347/A", "problem_id": "4528277"}
{"lang": "Python 2", "title": "339C - Xenia and Weights", "time": "92ms", "verdict": "WRONG_ANSWER", "memory": "0KB", "problem_link": "/problemset/problem/339/C", "problem_id": "4347982"}
{"lang": "Python 2", "title": "339C - Xenia and Weights", "time": "62ms", "verdict": "RUNTIME_ERROR", "memory": "0KB", "problem_link": "/problemset/problem/339/C", "problem_id": "4347564"}
{"lang": "Python 2", "title": "339B - Xenia and Ringroad", "time": "218ms", "verdict": "OK", "memory": "5500KB", "problem_link": "/problemset/problem/339/B", "problem_id": "4343738"}
{"lang": "Python 2", "title": "339A - Helpful Maths", "time": "92ms", "verdict": "OK", "memory": "0KB", "problem_link": "/problemset/problem/339/A", "problem_id": "4340556"}
